AUTHORS
LICENSE
MANIFEST.in
README.md
setup.py
classymq/VERSION
classymq/__init__.py
classymq/common.py
classymq/consumers.py
classymq/exchanges.py
classymq/factory.py
classymq/message.py
classymq/models.py
classymq/producers.py
classymq/protocol.py
classymq/queues.py
classymq/registry.py
classymq/service.py
classymq/spec.xml
classymq/synchronous.py
classymq/utils.py
classymq.egg-info/PKG-INFO
classymq.egg-info/SOURCES.txt
classymq.egg-info/dependency_links.txt
classymq.egg-info/requires.txt
classymq.egg-info/top_level.txt
classymq/api/__init__.py
classymq/api/base.py
classymq/api/common.py
classymq/api/consumer.py
classymq/api/exceptions.py
classymq/api/producer.py
classymq/event/__init__.py
classymq/event/common.py
classymq/event/consumer.py
classymq/event/events.py
classymq/event/producer.py
classymq/event/registry.py
classymq/lib/__init__.py
classymq/lib/slug.py
classymq/lib/uuid.py
classymq/tests/__init__.py
classymq/tests/base.py
classymq/tests/test_api.py
examples/__init__.py
examples/log/__init__.py
examples/log/common.py
examples/log/consumer.py
examples/log/handlers.py
examples/log/producer.py
examples/log/service.py
examples/log/settings.py