Metadata-Version: 1.1
Name: classymq
Version: 0.7.0
Summary: RabbitMQ class based library.
Home-page: https://github.com/gdoermann/classymq
Author: Greg Doermann
Author-email: gdoermann@gmail.com
License: BSD
Keywords: rabbitmq,amqp,messaging
Platform: UNKNOWN
Classifier: Environment :: Web Environment
Classifier: Environment :: Plugins
Classifier: License :: OSI Approved :: BSD License
Classifier: Operating System :: OS Independent
Classifier: Programming Language :: Python :: 2.7
Classifier: Topic :: Internet :: WWW/HTTP
Classifier: Topic :: Software Development :: Libraries :: Python Modules
